odoo/addons/mrp_bom_line_sequence/README.rst
odoo/addons/mrp_bom_line_sequence/__init__.py
odoo/addons/mrp_bom_line_sequence/__manifest__.py
odoo/addons/mrp_bom_line_sequence/i18n/hr.po
odoo/addons/mrp_bom_line_sequence/i18n/mrp_bom_line_sequence.pot
odoo/addons/mrp_bom_line_sequence/i18n/pt_BR.po
odoo/addons/mrp_bom_line_sequence/models/__init__.py
odoo/addons/mrp_bom_line_sequence/models/mrp.py
odoo/addons/mrp_bom_line_sequence/readme/CONTRIBUTORS.rst
odoo/addons/mrp_bom_line_sequence/readme/DESCRIPTION.rst
odoo/addons/mrp_bom_line_sequence/readme/USAGE.rst
odoo/addons/mrp_bom_line_sequence/static/description/icon.png
odoo/addons/mrp_bom_line_sequence/static/description/index.html
odoo/addons/mrp_bom_line_sequence/views/stock_view.xml
odoo12_addon_mrp_bom_line_sequence-12.0.1.0.1.dist-info/METADATA
odoo12_addon_mrp_bom_line_sequence-12.0.1.0.1.dist-info/WHEEL
odoo12_addon_mrp_bom_line_sequence-12.0.1.0.1.dist-info/top_level.txt
odoo12_addon_mrp_bom_line_sequence-12.0.1.0.1.dist-info/RECORD
